jupyterlite_repl_prerun/__init__.py
jupyterlite_repl_prerun/_version.py
jupyterlite_repl_prerun-0.2.0.data/data/share/jupyter/labextensions/jupyterlite-repl-prerun/package.json
jupyterlite_repl_prerun-0.2.0.data/data/share/jupyter/labextensions/jupyterlite-repl-prerun/static/568.d794d3d66d23dc14a2f4.js
jupyterlite_repl_prerun-0.2.0.data/data/share/jupyter/labextensions/jupyterlite-repl-prerun/static/747.a1a07690be9cf9e8e997.js
jupyterlite_repl_prerun-0.2.0.data/data/share/jupyter/labextensions/jupyterlite-repl-prerun/static/remoteEntry.837d91241593cb213d2f.js
jupyterlite_repl_prerun-0.2.0.data/data/share/jupyter/labextensions/jupyterlite-repl-prerun/static/style.js
jupyterlite_repl_prerun-0.2.0.data/data/share/jupyter/labextensions/jupyterlite-repl-prerun/static/third-party-licenses.json
jupyterlite_repl_prerun-0.2.0.data/data/share/jupyter/labextensions/jupyterlite-repl-prerun/install.json
jupyterlite_repl_prerun-0.2.0.dist-info/METADATA
jupyterlite_repl_prerun-0.2.0.dist-info/WHEEL
jupyterlite_repl_prerun-0.2.0.dist-info/licenses/LICENSE
jupyterlite_repl_prerun-0.2.0.dist-info/RECORD
