Metadata-Version: 2.1
Name: jupyterlite_repl_prerun
Version: 0.2.0
Summary: Jupyterlite extension to allow code to be pre-run in the repl app
Project-URL: Homepage, https://github.com/jobovy/jupyterlite-repl-prerun
Project-URL: Bug Tracker, https://github.com/jobovy/jupyterlite-repl-prerun/issues
Project-URL: Repository, https://github.com/jobovy/jupyterlite-repl-prerun.git
Author-email: Jo Bovy <bovy@astro.utoronto.ca>
License: BSD 3-Clause License
License-File: LICENSE
Classifier: Framework :: Jupyter
Classifier: Framework :: Jupyter :: JupyterLab
Classifier: Framework :: Jupyter :: JupyterLab :: 3
Classifier: Framework :: Jupyter :: JupyterLab :: Extensions
Classifier: Framework :: Jupyter :: JupyterLab :: Extensions :: Prebuilt
Classifier: License :: OSI Approved :: BSD License
Classifier: Programming Language :: Python
Classifier: Programming Language :: Python :: 3
Classifier: Programming Language :: Python :: 3.7
Classifier: Programming Language :: Python :: 3.8
Classifier: Programming Language :: Python :: 3.9
Classifier: Programming Language :: Python :: 3.10
Classifier: Programming Language :: Python :: 3.11
Requires-Python: >=3.7
